hackgame/__init__.py
hackgame/api.py
hackgame/auth.py
hackgame/docs.py
hackgame/models.py
hackgame/cli/__init__.py
hackgame/cli/__main__.py
hackgame/cli/api_wrapper.py
hackgame/cli/autocomplete.py
hackgame/cli/history.py
hackgame/cli/identifier_cache.py
hackgame/cli/persistence.py
hackgame/cli/update_notice.py
hackgame-0.0.28.dist-info/METADATA
hackgame-0.0.28.dist-info/WHEEL
hackgame-0.0.28.dist-info/entry_points.txt
hackgame-0.0.28.dist-info/top_level.txt
hackgame-0.0.28.dist-info/RECORD
